robot_core/__init__.py
robot_core/flow_executor.py
robot_core/flow_executor_main.py
robot_core/parse_function_definitions.py
robot_core/parse_function_definitions_main.py
robot_core/robot_debugger.py
robot_core/robot_debugger_main.py
robot_core/robot_interpreter.py
robot_core/robot_interpreter_main.py
robot_core-0.2.32.dist-info/METADATA
robot_core-0.2.32.dist-info/WHEEL
robot_core-0.2.32.dist-info/RECORD
