Metadata-Version: 2.4
Name: robot_core
Version: 0.2.32
Summary: robot core tools
Author: mance
Classifier: License :: OSI Approved :: MIT License
Classifier: Operating System :: OS Independent
Classifier: Programming Language :: Python :: 3
Requires-Python: >=3.11
Requires-Dist: debugpy
Requires-Dist: pydantic
